{
  "data_dictionary": {
    "metadata": {
      "size": { "-1": "small", "0": "average", "1": "large" },
      "apartment-friendly": { "0": "no", "1": "yes" },
      "barking-tendency": { "-1": "low", "0": "average", "1": "high" },
      "cat-social": { "-1": "antisocial", "0": "average", "1": "social" },
      "child-social": { "-1": "antisocial", "0": "average", "1": "social" },
      "dog-social": { "-1": "antisocial", "0": "average", "1": "social" },
      "exercise-needs": { "-1": "low", "0": "average", "1": "high" },
      "grooming": { "-1": "low", "0": "average", "1": "high" },
      "hypoallergenic": { "0": "no", "1": "yes" },
      "human-social": { "-1": "antisocial", "0": "average", "1": "social" },
      "shedding": { "-1": "low", "0": "average", "1": "high" },
      "stranger-social": { "-1": "antisocial", "0": "average", "1": "social" },
      "trainable": { "-1": "low", "0": "average", "1": "high" }
    }
  },
  "data": [
    {
      "n02085620-Chihuahua": {
        "metadata": {
          "size": 0,
          "apartment-friendly": 0,
          "barking-tendencies": 0,
          "cat-social": 0,
          "child-social": 0,
          "dog-social": 0,
          "exercise-needs": 0,
          "grooming": 0,
          "hypoallergenic": 0,
          "human-social": 0,
          "shedding": 0,
          "stranger-social": 0,
          "trainable": 0
        }
      }
    },
    {
      "n02085782-Japanese_spaniel": {
        "metadata": {
          "size": 0,
          "apartment-friendly": 0,
          "barking-tendencies": 0,
          "cat-social": 0,
          "child-social": 0,
          "dog-social": 0,
          "exercise-needs": 0,
          "grooming": 0,
          "hypoallergenic": 0,
          "human-social": 0,
          "shedding": 0,
          "stranger-social": 0,
          "trainable": 0
        }
      }
    },
    {
      "n02085936-Maltese_dog": {
        "metadata": {
          "size": 0,
          "apartment-friendly": 0,
          "barking-tendencies": 0,
          "cat-social": 0,
          "child-social": 0,
          "dog-social": 0,
          "exercise-needs": 0,
          "grooming": 0,
          "hypoallergenic": 0,
          "human-social": 0,
          "shedding": 0,
          "stranger-social": 0,
          "trainable": 0
        }
      }
    },
    {
      "n02086079-Pekinese": {
        "metadata": {
          "size": 0,
          "apartment-friendly": 0,
          "barking-tendencies": 0,
          "cat-social": 0,
          "child-social": 0,
          "dog-social": 0,
          "exercise-needs": 0,
          "grooming": 0,
          "hypoallergenic": 0,
          "human-social": 0,
          "shedding": 0,
          "stranger-social": 0,
          "trainable": 0
        }
      }
    },
    {
      "n02086240-Shih-Tzu": {
        "metadata": {
          "size": 0,
          "apartment-friendly": 0,
          "barking-tendencies": 0,
          "cat-social": 0,
          "child-social": 0,
          "dog-social": 0,
          "exercise-needs": 0,
          "grooming": 0,
          "hypoallergenic": 0,
          "human-social": 0,
          "shedding": 0,
          "stranger-social": 0,
          "trainable": 0
        }
      }
    },
    {
      "n02086646-Blenheim_spaniel": {
        "metadata": {
          "size": 0,
          "apartment-friendly": 0,
          "barking-tendencies": 0,
          "cat-social": 0,
          "child-social": 0,
          "dog-social": 0,
          "exercise-needs": 0,
          "grooming": 0,
          "hypoallergenic": 0,
          "human-social": 0,
          "shedding": 0,
          "stranger-social": 0,
          "trainable": 0
        }
      }
    },
    {
      "n02086910-papillon": {
        "metadata": {
          "size": 0,
          "apartment-friendly": 0,
          "barking-tendencies": 0,
          "cat-social": 0,
          "child-social": 0,
          "dog-social": 0,
          "exercise-needs": 0,
          "grooming": 0,
          "hypoallergenic": 0,
          "human-social": 0,
          "shedding": 0,
          "stranger-social": 0,
          "trainable": 0
        }
      }
    },
    {
      "n02087046-toy_terrier": {
        "metadata": {
          "size": 0,
          "apartment-friendly": 0,
          "barking-tendencies": 0,
          "cat-social": 0,
          "child-social": 0,
          "dog-social": 0,
          "exercise-needs": 0,
          "grooming": 0,
          "hypoallergenic": 0,
          "human-social": 0,
          "shedding": 0,
          "stranger-social": 0,
          "trainable": 0
        }
      }
    },
    {
      "n02087394-Rhodesian_ridgeback": {
        "metadata": {
          "size": 0,
          "apartment-friendly": 0,
          "barking-tendencies": 0,
          "cat-social": 0,
          "child-social": 0,
          "dog-social": 0,
          "exercise-needs": 0,
          "grooming": 0,
          "hypoallergenic": 0,
          "human-social": 0,
          "shedding": 0,
          "stranger-social": 0,
          "trainable": 0
        }
      }
    },
    {
      "n02088094-Afghan_hound": {
        "metadata": {
          "size": 1,
          "apartment-friendly": 0,
          "barking-tendencies": -1,
          "cat-social": -1,
          "child-social": 0,
          "dog-social": 0,
          "exercise-needs": 1,
          "grooming": 1,
          "hypoallergenic": 1,
          "human-social": 1,
          "shedding": 1,
          "stranger-social": -1,
          "trainable": -1
        }
      }
    },
    {
      "n02088238-basset": {
        "metadata": {
          "size": 0,
          "apartment-friendly": 0,
          "barking-tendencies": 0,
          "cat-social": 0,
          "child-social": 0,
          "dog-social": 0,
          "exercise-needs": 0,
          "grooming": 0,
          "hypoallergenic": 0,
          "human-social": 0,
          "shedding": 0,
          "stranger-social": 0,
          "trainable": 0
        }
      }
    },
    {
      "n02088364-beagle": {
        "metadata": {
          "size": 0,
          "apartment-friendly": 0,
          "barking-tendencies": 0,
          "cat-social": 0,
          "child-social": 0,
          "dog-social": 0,
          "exercise-needs": 0,
          "grooming": 0,
          "hypoallergenic": 0,
          "human-social": 0,
          "shedding": 0,
          "stranger-social": 0,
          "trainable": 0
        }
      }
    },
    {
      "n02088466-bloodhound": {
        "metadata": {
          "size": 0,
          "apartment-friendly": 0,
          "barking-tendencies": 0,
          "cat-social": 0,
          "child-social": 0,
          "dog-social": 0,
          "exercise-needs": 0,
          "grooming": 0,
          "hypoallergenic": 0,
          "human-social": 0,
          "shedding": 0,
          "stranger-social": 0,
          "trainable": 0
        }
      }
    },
    {
      "n02088632-bluetick": {
        "metadata": {
          "size": 0,
          "apartment-friendly": 0,
          "barking-tendencies": 0,
          "cat-social": 0,
          "child-social": 0,
          "dog-social": 0,
          "exercise-needs": 0,
          "grooming": 0,
          "hypoallergenic": 0,
          "human-social": 0,
          "shedding": 0,
          "stranger-social": 0,
          "trainable": 0
        }
      }
    },
    {
      "n02089078-black-and-tan_coonhound": {
        "metadata": {
          "size": 0,
          "apartment-friendly": 0,
          "barking-tendencies": 0,
          "cat-social": 0,
          "child-social": 0,
          "dog-social": 0,
          "exercise-needs": 0,
          "grooming": 0,
          "hypoallergenic": 0,
          "human-social": 0,
          "shedding": 0,
          "stranger-social": 0,
          "trainable": 0
        }
      }
    },
    {
      "n02089867-Walker_hound": {
        "metadata": {
          "size": 0,
          "apartment-friendly": 0,
          "barking-tendencies": 0,
          "cat-social": 0,
          "child-social": 0,
          "dog-social": 0,
          "exercise-needs": 0,
          "grooming": 0,
          "hypoallergenic": 0,
          "human-social": 0,
          "shedding": 0,
          "stranger-social": 0,
          "trainable": 0
        }
      }
    },
    {
      "n02089973-English_foxhound": {
        "metadata": {
          "size": 0,
          "apartment-friendly": 0,
          "barking-tendencies": 0,
          "cat-social": 0,
          "child-social": 0,
          "dog-social": 0,
          "exercise-needs": 0,
          "grooming": 0,
          "hypoallergenic": 0,
          "human-social": 0,
          "shedding": 0,
          "stranger-social": 0,
          "trainable": 0
        }
      }
    },
    {
      "n02090379-redbone": {
        "metadata": {
          "size": 0,
          "apartment-friendly": 0,
          "barking-tendencies": 0,
          "cat-social": 0,
          "child-social": 0,
          "dog-social": 0,
          "exercise-needs": 0,
          "grooming": 0,
          "hypoallergenic": 0,
          "human-social": 0,
          "shedding": 0,
          "stranger-social": 0,
          "trainable": 0
        }
      }
    },
    {
      "n02090622-borzoi": {
        "metadata": {
          "size": 0,
          "apartment-friendly": 0,
          "barking-tendencies": 0,
          "cat-social": 0,
          "child-social": 0,
          "dog-social": 0,
          "exercise-needs": 0,
          "grooming": 0,
          "hypoallergenic": 0,
          "human-social": 0,
          "shedding": 0,
          "stranger-social": 0,
          "trainable": 0
        }
      }
    },
    {
      "n02090721-Irish_wolfhound": {
        "metadata": {
          "size": 0,
          "apartment-friendly": 0,
          "barking-tendencies": 0,
          "cat-social": 0,
          "child-social": 0,
          "dog-social": 0,
          "exercise-needs": 0,
          "grooming": 0,
          "hypoallergenic": 0,
          "human-social": 0,
          "shedding": 0,
          "stranger-social": 0,
          "trainable": 0
        }
      }
    },
    {
      "n02091032-Italian_greyhound": {
        "metadata": {
          "size": 0,
          "apartment-friendly": 0,
          "barking-tendencies": 0,
          "cat-social": 0,
          "child-social": 0,
          "dog-social": 0,
          "exercise-needs": 0,
          "grooming": 0,
          "hypoallergenic": 0,
          "human-social": 0,
          "shedding": 0,
          "stranger-social": 0,
          "trainable": 0
        }
      }
    },
    {
      "n02091134-whippet": {
        "metadata": {
          "size": 0,
          "apartment-friendly": 0,
          "barking-tendencies": 0,
          "cat-social": 0,
          "child-social": 0,
          "dog-social": 0,
          "exercise-needs": 0,
          "grooming": 0,
          "hypoallergenic": 0,
          "human-social": 0,
          "shedding": 0,
          "stranger-social": 0,
          "trainable": 0
        }
      }
    },
    {
      "n02091244-Ibizan_hound": {
        "metadata": {
          "size": 0,
          "apartment-friendly": 0,
          "barking-tendencies": 0,
          "cat-social": 0,
          "child-social": 0,
          "dog-social": 0,
          "exercise-needs": 0,
          "grooming": 0,
          "hypoallergenic": 0,
          "human-social": 0,
          "shedding": 0,
          "stranger-social": 0,
          "trainable": 0
        }
      }
    },
    {
      "n02091467-Norwegian_elkhound": {
        "metadata": {
          "size": 0,
          "apartment-friendly": 0,
          "barking-tendencies": 0,
          "cat-social": 0,
          "child-social": 0,
          "dog-social": 0,
          "exercise-needs": 0,
          "grooming": 0,
          "hypoallergenic": 0,
          "human-social": 0,
          "shedding": 0,
          "stranger-social": 0,
          "trainable": 0
        }
      }
    },
    {
      "n02091635-otterhound": {
        "metadata": {
          "size": 0,
          "apartment-friendly": 0,
          "barking-tendencies": 0,
          "cat-social": 0,
          "child-social": 0,
          "dog-social": 0,
          "exercise-needs": 0,
          "grooming": 0,
          "hypoallergenic": 0,
          "human-social": 0,
          "shedding": 0,
          "stranger-social": 0,
          "trainable": 0
        }
      }
    },
    {
      "n02091831-Saluki": {
        "metadata": {
          "size": 0,
          "apartment-friendly": 0,
          "barking-tendencies": 0,
          "cat-social": 0,
          "child-social": 0,
          "dog-social": 0,
          "exercise-needs": 0,
          "grooming": 0,
          "hypoallergenic": 0,
          "human-social": 0,
          "shedding": 0,
          "stranger-social": 0,
          "trainable": 0
        }
      }
    },
    {
      "n02092002-Scottish_deerhound": {
        "metadata": {
          "size": 0,
          "apartment-friendly": 0,
          "barking-tendencies": 0,
          "cat-social": 0,
          "child-social": 0,
          "dog-social": 0,
          "exercise-needs": 0,
          "grooming": 0,
          "hypoallergenic": 0,
          "human-social": 0,
          "shedding": 0,
          "stranger-social": 0,
          "trainable": 0
        }
      }
    },
    {
      "n02092339-Weimaraner": {
        "metadata": {
          "size": 0,
          "apartment-friendly": 0,
          "barking-tendencies": 0,
          "cat-social": 0,
          "child-social": 0,
          "dog-social": 0,
          "exercise-needs": 0,
          "grooming": 0,
          "hypoallergenic": 0,
          "human-social": 0,
          "shedding": 0,
          "stranger-social": 0,
          "trainable": 0
        }
      }
    },
    {
      "n02093256-Staffordshire_bullterrier": {
        "metadata": {
          "size": 0,
          "apartment-friendly": 0,
          "barking-tendencies": 0,
          "cat-social": 0,
          "child-social": 0,
          "dog-social": 0,
          "exercise-needs": 0,
          "grooming": 0,
          "hypoallergenic": 0,
          "human-social": 0,
          "shedding": 0,
          "stranger-social": 0,
          "trainable": 0
        }
      }
    },
    {
      "n02093428-American_Staffordshire_terrier": {
        "metadata": {
          "size": 0,
          "apartment-friendly": -1,
          "barking-tendencies": 0,
          "cat-social": -1,
          "child-social": 1,
          "dog-social": -1,
          "exercise-needs": 1,
          "grooming": -1,
          "hypoallergenic": 0,
          "human-social": 1,
          "shedding": -1,
          "stranger-social": 1,
          "trainable": 1
        }
      }
    },
    {
      "n02093647-Bedlington_terrier": {
        "metadata": {
          "size": 0,
          "apartment-friendly": 0,
          "barking-tendencies": 0,
          "cat-social": 0,
          "child-social": 0,
          "dog-social": 0,
          "exercise-needs": 0,
          "grooming": 0,
          "hypoallergenic": 0,
          "human-social": 0,
          "shedding": 0,
          "stranger-social": 0,
          "trainable": 0
        }
      }
    },
    {
      "n02093754-Border_terrier": {
        "metadata": {
          "size": 0,
          "apartment-friendly": 0,
          "barking-tendencies": 0,
          "cat-social": 0,
          "child-social": 0,
          "dog-social": 0,
          "exercise-needs": 0,
          "grooming": 0,
          "hypoallergenic": 0,
          "human-social": 0,
          "shedding": 0,
          "stranger-social": 0,
          "trainable": 0
        }
      }
    },
    {
      "n02093859-Kerry_blue_terrier": {
        "metadata": {
          "size": 0,
          "apartment-friendly": 0,
          "barking-tendencies": 0,
          "cat-social": 0,
          "child-social": 0,
          "dog-social": 0,
          "exercise-needs": 0,
          "grooming": 0,
          "hypoallergenic": 0,
          "human-social": 0,
          "shedding": 0,
          "stranger-social": 0,
          "trainable": 0
        }
      }
    },
    {
      "n02093991-Irish_terrier": {
        "metadata": {
          "size": 0,
          "apartment-friendly": 0,
          "barking-tendencies": 0,
          "cat-social": 0,
          "child-social": 0,
          "dog-social": 0,
          "exercise-needs": 0,
          "grooming": 0,
          "hypoallergenic": 0,
          "human-social": 0,
          "shedding": 0,
          "stranger-social": 0,
          "trainable": 0
        }
      }
    },
    {
      "n02094114-Norfolk_terrier": {
        "metadata": {
          "size": 0,
          "apartment-friendly": 0,
          "barking-tendencies": 0,
          "cat-social": 0,
          "child-social": 0,
          "dog-social": 0,
          "exercise-needs": 0,
          "grooming": 0,
          "hypoallergenic": 0,
          "human-social": 0,
          "shedding": 0,
          "stranger-social": 0,
          "trainable": 0
        }
      }
    },
    {
      "n02094258-Norwich_terrier": {
        "metadata": {
          "size": 0,
          "apartment-friendly": 0,
          "barking-tendencies": 0,
          "cat-social": 0,
          "child-social": 0,
          "dog-social": 0,
          "exercise-needs": 0,
          "grooming": 0,
          "hypoallergenic": 0,
          "human-social": 0,
          "shedding": 0,
          "stranger-social": 0,
          "trainable": 0
        }
      }
    },
    {
      "n02094433-Yorkshire_terrier": {
        "metadata": {
          "size": 0,
          "apartment-friendly": 0,
          "barking-tendencies": 0,
          "cat-social": 0,
          "child-social": 0,
          "dog-social": 0,
          "exercise-needs": 0,
          "grooming": 0,
          "hypoallergenic": 0,
          "human-social": 0,
          "shedding": 0,
          "stranger-social": 0,
          "trainable": 0
        }
      }
    },
    {
      "n02095314-wire-haired_fox_terrier": {
        "metadata": {
          "size": 0,
          "apartment-friendly": 0,
          "barking-tendencies": 0,
          "cat-social": 0,
          "child-social": 0,
          "dog-social": 0,
          "exercise-needs": 0,
          "grooming": 0,
          "hypoallergenic": 0,
          "human-social": 0,
          "shedding": 0,
          "stranger-social": 0,
          "trainable": 0
        }
      }
    },
    {
      "n02095570-Lakeland_terrier": {
        "metadata": {
          "size": 0,
          "apartment-friendly": 0,
          "barking-tendencies": 0,
          "cat-social": 0,
          "child-social": 0,
          "dog-social": 0,
          "exercise-needs": 0,
          "grooming": 0,
          "hypoallergenic": 0,
          "human-social": 0,
          "shedding": 0,
          "stranger-social": 0,
          "trainable": 0
        }
      }
    },
    {
      "n02095889-Sealyham_terrier": {
        "metadata": {
          "size": 0,
          "apartment-friendly": 0,
          "barking-tendencies": 0,
          "cat-social": 0,
          "child-social": 0,
          "dog-social": 0,
          "exercise-needs": 0,
          "grooming": 0,
          "hypoallergenic": 0,
          "human-social": 0,
          "shedding": 0,
          "stranger-social": 0,
          "trainable": 0
        }
      }
    },
    {
      "n02096051-Airedale": {
        "metadata": {
          "size": 0,
          "apartment-friendly": 0,
          "barking-tendencies": 0,
          "cat-social": -1,
          "child-social": 0,
          "dog-social": -1,
          "exercise-needs": 1,
          "grooming": 1,
          "hypoallergenic": 1,
          "human-social": 1,
          "shedding": 0,
          "stranger-social": -1,
          "trainable": 0
        }
      }
    },
    {
      "n02096177-cairn": {
        "metadata": {
          "size": 0,
          "apartment-friendly": 0,
          "barking-tendencies": 0,
          "cat-social": 0,
          "child-social": 0,
          "dog-social": 0,
          "exercise-needs": 0,
          "grooming": 0,
          "hypoallergenic": 0,
          "human-social": 0,
          "shedding": 0,
          "stranger-social": 0,
          "trainable": 0
        }
      }
    },
    {
      "n02096294-Australian_terrier": {
        "metadata": {
          "size": -1,
          "apartment-friendly": 0,
          "barking-tendencies": 0,
          "cat-social": -1,
          "child-social": 1,
          "dog-social": -1,
          "exercise-needs": 1,
          "grooming": 0,
          "hypoallergenic": 1,
          "human-social": 1,
          "shedding": -1,
          "stranger-social": 0,
          "trainable": 1
        }
      }
    },
    {
      "n02096437-Dandie_Dinmont": {
        "metadata": {
          "size": 0,
          "apartment-friendly": 0,
          "barking-tendencies": 0,
          "cat-social": 0,
          "child-social": 0,
          "dog-social": 0,
          "exercise-needs": 0,
          "grooming": 0,
          "hypoallergenic": 0,
          "human-social": 0,
          "shedding": 0,
          "stranger-social": 0,
          "trainable": 0
        }
      }
    },
    {
      "n02096585-Boston_bull": {
        "metadata": {
          "size": 0,
          "apartment-friendly": 0,
          "barking-tendencies": 0,
          "cat-social": 0,
          "child-social": 0,
          "dog-social": 0,
          "exercise-needs": 0,
          "grooming": 0,
          "hypoallergenic": 0,
          "human-social": 0,
          "shedding": 0,
          "stranger-social": 0,
          "trainable": 0
        }
      }
    },
    {
      "n02097047-miniature_schnauzer": {
        "metadata": {
          "size": 0,
          "apartment-friendly": 0,
          "barking-tendencies": 0,
          "cat-social": 0,
          "child-social": 0,
          "dog-social": 0,
          "exercise-needs": 0,
          "grooming": 0,
          "hypoallergenic": 0,
          "human-social": 0,
          "shedding": 0,
          "stranger-social": 0,
          "trainable": 0
        }
      }
    },
    {
      "n02097130-giant_schnauzer": {
        "metadata": {
          "size": 0,
          "apartment-friendly": 0,
          "barking-tendencies": 0,
          "cat-social": 0,
          "child-social": 0,
          "dog-social": 0,
          "exercise-needs": 0,
          "grooming": 0,
          "hypoallergenic": 0,
          "human-social": 0,
          "shedding": 0,
          "stranger-social": 0,
          "trainable": 0
        }
      }
    },
    {
      "n02097209-standard_schnauzer": {
        "metadata": {
          "size": 0,
          "apartment-friendly": 0,
          "barking-tendencies": 0,
          "cat-social": 0,
          "child-social": 0,
          "dog-social": 0,
          "exercise-needs": 0,
          "grooming": 0,
          "hypoallergenic": 0,
          "human-social": 0,
          "shedding": 0,
          "stranger-social": 0,
          "trainable": 0
        }
      }
    },
    {
      "n02097298-Scotch_terrier": {
        "metadata": {
          "size": 0,
          "apartment-friendly": 0,
          "barking-tendencies": 0,
          "cat-social": 0,
          "child-social": 0,
          "dog-social": 0,
          "exercise-needs": 0,
          "grooming": 0,
          "hypoallergenic": 0,
          "human-social": 0,
          "shedding": 0,
          "stranger-social": 0,
          "trainable": 0
        }
      }
    },
    {
      "n02097474-Tibetan_terrier": {
        "metadata": {
          "size": 0,
          "apartment-friendly": 0,
          "barking-tendencies": 0,
          "cat-social": 0,
          "child-social": 0,
          "dog-social": 0,
          "exercise-needs": 0,
          "grooming": 0,
          "hypoallergenic": 0,
          "human-social": 0,
          "shedding": 0,
          "stranger-social": 0,
          "trainable": 0
        }
      }
    },
    {
      "n02097658-silky_terrier": {
        "metadata": {
          "size": 0,
          "apartment-friendly": 0,
          "barking-tendencies": 0,
          "cat-social": 0,
          "child-social": 0,
          "dog-social": 0,
          "exercise-needs": 0,
          "grooming": 0,
          "hypoallergenic": 0,
          "human-social": 0,
          "shedding": 0,
          "stranger-social": 0,
          "trainable": 0
        }
      }
    },
    {
      "n02098105-soft-coated_wheaten_terrier": {
        "metadata": {
          "size": 0,
          "apartment-friendly": 0,
          "barking-tendencies": 0,
          "cat-social": 0,
          "child-social": 0,
          "dog-social": 0,
          "exercise-needs": 0,
          "grooming": 0,
          "hypoallergenic": 0,
          "human-social": 0,
          "shedding": 0,
          "stranger-social": 0,
          "trainable": 0
        }
      }
    },
    {
      "n02098286-West_Highland_white_terrier": {
        "metadata": {
          "size": 0,
          "apartment-friendly": 0,
          "barking-tendencies": 0,
          "cat-social": 0,
          "child-social": 0,
          "dog-social": 0,
          "exercise-needs": 0,
          "grooming": 0,
          "hypoallergenic": 0,
          "human-social": 0,
          "shedding": 0,
          "stranger-social": 0,
          "trainable": 0
        }
      }
    },
    {
      "n02098413-Lhasa": {
        "metadata": {
          "size": 0,
          "apartment-friendly": 0,
          "barking-tendencies": 0,
          "cat-social": 0,
          "child-social": 0,
          "dog-social": 0,
          "exercise-needs": 0,
          "grooming": 0,
          "hypoallergenic": 0,
          "human-social": 0,
          "shedding": 0,
          "stranger-social": 0,
          "trainable": 0
        }
      }
    },
    {
      "n02099267-flat-coated_retriever": {
        "metadata": {
          "size": 0,
          "apartment-friendly": 0,
          "barking-tendencies": 0,
          "cat-social": 0,
          "child-social": 0,
          "dog-social": 0,
          "exercise-needs": 0,
          "grooming": 0,
          "hypoallergenic": 0,
          "human-social": 0,
          "shedding": 0,
          "stranger-social": 0,
          "trainable": 0
        }
      }
    },
    {
      "n02099429-curly-coated_retriever": {
        "metadata": {
          "size": 0,
          "apartment-friendly": 0,
          "barking-tendencies": 0,
          "cat-social": 0,
          "child-social": 0,
          "dog-social": 0,
          "exercise-needs": 0,
          "grooming": 0,
          "hypoallergenic": 0,
          "human-social": 0,
          "shedding": 0,
          "stranger-social": 0,
          "trainable": 0
        }
      }
    },
    {
      "n02099601-golden_retriever": {
        "metadata": {
          "size": 0,
          "apartment-friendly": 0,
          "barking-tendencies": 0,
          "cat-social": 0,
          "child-social": 0,
          "dog-social": 0,
          "exercise-needs": 0,
          "grooming": 0,
          "hypoallergenic": 0,
          "human-social": 0,
          "shedding": 0,
          "stranger-social": 0,
          "trainable": 0
        }
      }
    },
    {
      "n02099712-Labrador_retriever": {
        "metadata": {
          "size": 0,
          "apartment-friendly": 0,
          "barking-tendencies": 0,
          "cat-social": 0,
          "child-social": 0,
          "dog-social": 0,
          "exercise-needs": 0,
          "grooming": 0,
          "hypoallergenic": 0,
          "human-social": 0,
          "shedding": 0,
          "stranger-social": 0,
          "trainable": 0
        }
      }
    },
    {
      "n02099849-Chesapeake_Bay_retriever": {
        "metadata": {
          "size": 0,
          "apartment-friendly": 0,
          "barking-tendencies": 0,
          "cat-social": 0,
          "child-social": 0,
          "dog-social": 0,
          "exercise-needs": 0,
          "grooming": 0,
          "hypoallergenic": 0,
          "human-social": 0,
          "shedding": 0,
          "stranger-social": 0,
          "trainable": 0
        }
      }
    },
    {
      "n02100236-German_short-haired_pointer": {
        "metadata": {
          "size": 0,
          "apartment-friendly": 0,
          "barking-tendencies": 0,
          "cat-social": 0,
          "child-social": 0,
          "dog-social": 0,
          "exercise-needs": 0,
          "grooming": 0,
          "hypoallergenic": 0,
          "human-social": 0,
          "shedding": 0,
          "stranger-social": 0,
          "trainable": 0
        }
      }
    },
    {
      "n02100583-vizsla": {
        "metadata": {
          "size": 0,
          "apartment-friendly": 0,
          "barking-tendencies": 0,
          "cat-social": 0,
          "child-social": 0,
          "dog-social": 0,
          "exercise-needs": 0,
          "grooming": 0,
          "hypoallergenic": 0,
          "human-social": 0,
          "shedding": 0,
          "stranger-social": 0,
          "trainable": 0
        }
      }
    },
    {
      "n02100735-English_setter": {
        "metadata": {
          "size": 0,
          "apartment-friendly": 0,
          "barking-tendencies": 0,
          "cat-social": 0,
          "child-social": 0,
          "dog-social": 0,
          "exercise-needs": 0,
          "grooming": 0,
          "hypoallergenic": 0,
          "human-social": 0,
          "shedding": 0,
          "stranger-social": 0,
          "trainable": 0
        }
      }
    },
    {
      "n02100877-Irish_setter": {
        "metadata": {
          "size": 0,
          "apartment-friendly": 0,
          "barking-tendencies": 0,
          "cat-social": 0,
          "child-social": 0,
          "dog-social": 0,
          "exercise-needs": 0,
          "grooming": 0,
          "hypoallergenic": 0,
          "human-social": 0,
          "shedding": 0,
          "stranger-social": 0,
          "trainable": 0
        }
      }
    },
    {
      "n02101006-Gordon_setter": {
        "metadata": {
          "size": 0,
          "apartment-friendly": 0,
          "barking-tendencies": 0,
          "cat-social": 0,
          "child-social": 0,
          "dog-social": 0,
          "exercise-needs": 0,
          "grooming": 0,
          "hypoallergenic": 0,
          "human-social": 0,
          "shedding": 0,
          "stranger-social": 0,
          "trainable": 0
        }
      }
    },
    {
      "n02101388-Brittany_spaniel": {
        "metadata": {
          "size": 0,
          "apartment-friendly": 0,
          "barking-tendencies": 0,
          "cat-social": 0,
          "child-social": 0,
          "dog-social": 0,
          "exercise-needs": 0,
          "grooming": 0,
          "hypoallergenic": 0,
          "human-social": 0,
          "shedding": 0,
          "stranger-social": 0,
          "trainable": 0
        }
      }
    },
    {
      "n02101556-clumber": {
        "metadata": {
          "size": 0,
          "apartment-friendly": 0,
          "barking-tendencies": 0,
          "cat-social": 0,
          "child-social": 0,
          "dog-social": 0,
          "exercise-needs": 0,
          "grooming": 0,
          "hypoallergenic": 0,
          "human-social": 0,
          "shedding": 0,
          "stranger-social": 0,
          "trainable": 0
        }
      }
    },
    {
      "n02102040-English_springer": {
        "metadata": {
          "size": 0,
          "apartment-friendly": 0,
          "barking-tendencies": 0,
          "cat-social": 0,
          "child-social": 0,
          "dog-social": 0,
          "exercise-needs": 0,
          "grooming": 0,
          "hypoallergenic": 0,
          "human-social": 0,
          "shedding": 0,
          "stranger-social": 0,
          "trainable": 0
        }
      }
    },
    {
      "n02102177-Welsh_springer_spaniel": {
        "metadata": {
          "size": 0,
          "apartment-friendly": 0,
          "barking-tendencies": 0,
          "cat-social": 0,
          "child-social": 0,
          "dog-social": 0,
          "exercise-needs": 0,
          "grooming": 0,
          "hypoallergenic": 0,
          "human-social": 0,
          "shedding": 0,
          "stranger-social": 0,
          "trainable": 0
        }
      }
    },
    {
      "n02102318-cocker_spaniel": {
        "metadata": {
          "size": 0,
          "apartment-friendly": 0,
          "barking-tendencies": 0,
          "cat-social": 0,
          "child-social": 0,
          "dog-social": 0,
          "exercise-needs": 0,
          "grooming": 0,
          "hypoallergenic": 0,
          "human-social": 0,
          "shedding": 0,
          "stranger-social": 0,
          "trainable": 0
        }
      }
    },
    {
      "n02102480-Sussex_spaniel": {
        "metadata": {
          "size": 0,
          "apartment-friendly": 0,
          "barking-tendencies": 0,
          "cat-social": 0,
          "child-social": 0,
          "dog-social": 0,
          "exercise-needs": 0,
          "grooming": 0,
          "hypoallergenic": 0,
          "human-social": 0,
          "shedding": 0,
          "stranger-social": 0,
          "trainable": 0
        }
      }
    },
    {
      "n02102973-Irish_water_spaniel": {
        "metadata": {
          "size": 0,
          "apartment-friendly": 0,
          "barking-tendencies": 0,
          "cat-social": 0,
          "child-social": 0,
          "dog-social": 0,
          "exercise-needs": 0,
          "grooming": 0,
          "hypoallergenic": 0,
          "human-social": 0,
          "shedding": 0,
          "stranger-social": 0,
          "trainable": 0
        }
      }
    },
    {
      "n02104029-kuvasz": {
        "metadata": {
          "size": 0,
          "apartment-friendly": 0,
          "barking-tendencies": 0,
          "cat-social": 0,
          "child-social": 0,
          "dog-social": 0,
          "exercise-needs": 0,
          "grooming": 0,
          "hypoallergenic": 0,
          "human-social": 0,
          "shedding": 0,
          "stranger-social": 0,
          "trainable": 0
        }
      }
    },
    {
      "n02104365-schipperke": {
        "metadata": {
          "size": 0,
          "apartment-friendly": 0,
          "barking-tendencies": 0,
          "cat-social": 0,
          "child-social": 0,
          "dog-social": 0,
          "exercise-needs": 0,
          "grooming": 0,
          "hypoallergenic": 0,
          "human-social": 0,
          "shedding": 0,
          "stranger-social": 0,
          "trainable": 0
        }
      }
    },
    {
      "n02105056-groenendael": {
        "metadata": {
          "size": 0,
          "apartment-friendly": 0,
          "barking-tendencies": 0,
          "cat-social": 0,
          "child-social": 0,
          "dog-social": 0,
          "exercise-needs": 0,
          "grooming": 0,
          "hypoallergenic": 0,
          "human-social": 0,
          "shedding": 0,
          "stranger-social": 0,
          "trainable": 0
        }
      }
    },
    {
      "n02105162-malinois": {
        "metadata": {
          "size": 0,
          "apartment-friendly": 0,
          "barking-tendencies": 0,
          "cat-social": 0,
          "child-social": 0,
          "dog-social": 0,
          "exercise-needs": 0,
          "grooming": 0,
          "hypoallergenic": 0,
          "human-social": 0,
          "shedding": 0,
          "stranger-social": 0,
          "trainable": 0
        }
      }
    },
    {
      "n02105251-briard": {
        "metadata": {
          "size": 0,
          "apartment-friendly": 0,
          "barking-tendencies": 0,
          "cat-social": 0,
          "child-social": 0,
          "dog-social": 0,
          "exercise-needs": 0,
          "grooming": 0,
          "hypoallergenic": 0,
          "human-social": 0,
          "shedding": 0,
          "stranger-social": 0,
          "trainable": 0
        }
      }
    },
    {
      "n02105412-kelpie": {
        "metadata": {
          "size": 0,
          "apartment-friendly": 0,
          "barking-tendencies": 0,
          "cat-social": 0,
          "child-social": 0,
          "dog-social": 0,
          "exercise-needs": 0,
          "grooming": 0,
          "hypoallergenic": 0,
          "human-social": 0,
          "shedding": 0,
          "stranger-social": 0,
          "trainable": 0
        }
      }
    },
    {
      "n02105505-komondor": {
        "metadata": {
          "size": 0,
          "apartment-friendly": 0,
          "barking-tendencies": 0,
          "cat-social": 0,
          "child-social": 0,
          "dog-social": 0,
          "exercise-needs": 0,
          "grooming": 0,
          "hypoallergenic": 0,
          "human-social": 0,
          "shedding": 0,
          "stranger-social": 0,
          "trainable": 0
        }
      }
    },
    {
      "n02105641-Old_English_sheepdog": {
        "metadata": {
          "size": 0,
          "apartment-friendly": 0,
          "barking-tendencies": 0,
          "cat-social": 0,
          "child-social": 0,
          "dog-social": 0,
          "exercise-needs": 0,
          "grooming": 0,
          "hypoallergenic": 0,
          "human-social": 0,
          "shedding": 0,
          "stranger-social": 0,
          "trainable": 0
        }
      }
    },
    {
      "n02105855-Shetland_sheepdog": {
        "metadata": {
          "size": 0,
          "apartment-friendly": 0,
          "barking-tendencies": 0,
          "cat-social": 0,
          "child-social": 0,
          "dog-social": 0,
          "exercise-needs": 0,
          "grooming": 0,
          "hypoallergenic": 0,
          "human-social": 0,
          "shedding": 0,
          "stranger-social": 0,
          "trainable": 0
        }
      }
    },
    {
      "n02106030-collie": {
        "metadata": {
          "size": 0,
          "apartment-friendly": 0,
          "barking-tendencies": 0,
          "cat-social": 0,
          "child-social": 0,
          "dog-social": 0,
          "exercise-needs": 0,
          "grooming": 0,
          "hypoallergenic": 0,
          "human-social": 0,
          "shedding": 0,
          "stranger-social": 0,
          "trainable": 0
        }
      }
    },
    {
      "n02106166-Border_collie": {
        "metadata": {
          "size": 0,
          "apartment-friendly": 0,
          "barking-tendencies": 0,
          "cat-social": 0,
          "child-social": 0,
          "dog-social": 0,
          "exercise-needs": 0,
          "grooming": 0,
          "hypoallergenic": 0,
          "human-social": 0,
          "shedding": 0,
          "stranger-social": 0,
          "trainable": 0
        }
      }
    },
    {
      "n02106382-Bouvier_des_Flandres": {
        "metadata": {
          "size": 0,
          "apartment-friendly": 0,
          "barking-tendencies": 0,
          "cat-social": 0,
          "child-social": 0,
          "dog-social": 0,
          "exercise-needs": 0,
          "grooming": 0,
          "hypoallergenic": 0,
          "human-social": 0,
          "shedding": 0,
          "stranger-social": 0,
          "trainable": 0
        }
      }
    },
    {
      "n02106550-Rottweiler": {
        "metadata": {
          "size": 0,
          "apartment-friendly": 0,
          "barking-tendencies": 0,
          "cat-social": 0,
          "child-social": 0,
          "dog-social": 0,
          "exercise-needs": 0,
          "grooming": 0,
          "hypoallergenic": 0,
          "human-social": 0,
          "shedding": 0,
          "stranger-social": 0,
          "trainable": 0
        }
      }
    },
    {
      "n02106662-German_shepherd": {
        "metadata": {
          "size": 0,
          "apartment-friendly": 0,
          "barking-tendencies": 0,
          "cat-social": 0,
          "child-social": 0,
          "dog-social": 0,
          "exercise-needs": 0,
          "grooming": 0,
          "hypoallergenic": 0,
          "human-social": 0,
          "shedding": 0,
          "stranger-social": 0,
          "trainable": 0
        }
      }
    },
    {
      "n02107142-Doberman": {
        "metadata": {
          "size": 0,
          "apartment-friendly": 0,
          "barking-tendencies": 0,
          "cat-social": 0,
          "child-social": 0,
          "dog-social": 0,
          "exercise-needs": 0,
          "grooming": 0,
          "hypoallergenic": 0,
          "human-social": 0,
          "shedding": 0,
          "stranger-social": 0,
          "trainable": 0
        }
      }
    },
    {
      "n02107312-miniature_pinscher": {
        "metadata": {
          "size": 0,
          "apartment-friendly": 0,
          "barking-tendencies": 0,
          "cat-social": 0,
          "child-social": 0,
          "dog-social": 0,
          "exercise-needs": 0,
          "grooming": 0,
          "hypoallergenic": 0,
          "human-social": 0,
          "shedding": 0,
          "stranger-social": 0,
          "trainable": 0
        }
      }
    },
    {
      "n02107574-Greater_Swiss_Mountain_dog": {
        "metadata": {
          "size": 0,
          "apartment-friendly": 0,
          "barking-tendencies": 0,
          "cat-social": 0,
          "child-social": 0,
          "dog-social": 0,
          "exercise-needs": 0,
          "grooming": 0,
          "hypoallergenic": 0,
          "human-social": 0,
          "shedding": 0,
          "stranger-social": 0,
          "trainable": 0
        }
      }
    },
    {
      "n02107683-Bernese_mountain_dog": {
        "metadata": {
          "size": 0,
          "apartment-friendly": 0,
          "barking-tendencies": 0,
          "cat-social": 0,
          "child-social": 0,
          "dog-social": 0,
          "exercise-needs": 0,
          "grooming": 0,
          "hypoallergenic": 0,
          "human-social": 0,
          "shedding": 0,
          "stranger-social": 0,
          "trainable": 0
        }
      }
    },
    {
      "n02107908-Appenzeller": {
        "metadata": {
          "size": 0,
          "apartment-friendly": 0,
          "barking-tendencies": 0,
          "cat-social": 0,
          "child-social": 0,
          "dog-social": 0,
          "exercise-needs": 0,
          "grooming": 0,
          "hypoallergenic": 0,
          "human-social": 0,
          "shedding": 0,
          "stranger-social": 0,
          "trainable": 1
        }
      }
    },
    {
      "n02108000-EntleBucher": {
        "metadata": {
          "size": 0,
          "apartment-friendly": -1,
          "barking-tendencies": 0,
          "cat-social": 0,
          "child-social": 1,
          "dog-social": 0,
          "exercise-needs": 0,
          "grooming": 0,
          "hypoallergenic": 0,
          "human-social": 1,
          "shedding": 0,
          "stranger-social": -1,
          "trainable": 0
        }
      }
    },
    {
      "n02108089-boxer": {
        "metadata": {
          "size": 0,
          "apartment-friendly": 0,
          "barking-tendencies": 0,
          "cat-social": 0,
          "child-social": 0,
          "dog-social": 0,
          "exercise-needs": 0,
          "grooming": 0,
          "hypoallergenic": 0,
          "human-social": 0,
          "shedding": 0,
          "stranger-social": 0,
          "trainable": 0
        }
      }
    },
    {
      "n02108422-bull_mastiff": {
        "metadata": {
          "size": 0,
          "apartment-friendly": 0,
          "barking-tendencies": 0,
          "cat-social": 0,
          "child-social": 0,
          "dog-social": 0,
          "exercise-needs": 0,
          "grooming": 0,
          "hypoallergenic": 0,
          "human-social": 0,
          "shedding": 0,
          "stranger-social": 0,
          "trainable": 0
        }
      }
    },
    {
      "n02108551-Tibetan_mastiff": {
        "metadata": {
          "size": 0,
          "apartment-friendly": 0,
          "barking-tendencies": 0,
          "cat-social": 0,
          "child-social": 0,
          "dog-social": 0,
          "exercise-needs": 0,
          "grooming": 0,
          "hypoallergenic": 0,
          "human-social": 0,
          "shedding": 0,
          "stranger-social": 0,
          "trainable": 0
        }
      }
    },
    {
      "n02108915-French_bulldog": {
        "metadata": {
          "size": 0,
          "apartment-friendly": 0,
          "barking-tendencies": 0,
          "cat-social": 0,
          "child-social": 0,
          "dog-social": 0,
          "exercise-needs": 0,
          "grooming": 0,
          "hypoallergenic": 0,
          "human-social": 0,
          "shedding": 0,
          "stranger-social": 0,
          "trainable": 0
        }
      }
    },
    {
      "n02109047-Great_Dane": {
        "metadata": {
          "size": 0,
          "apartment-friendly": 0,
          "barking-tendencies": 0,
          "cat-social": 0,
          "child-social": 0,
          "dog-social": 0,
          "exercise-needs": 0,
          "grooming": 0,
          "hypoallergenic": 0,
          "human-social": 0,
          "shedding": 0,
          "stranger-social": 0,
          "trainable": 0
        }
      }
    },
    {
      "n02109525-Saint_Bernard": {
        "metadata": {
          "size": 0,
          "apartment-friendly": 0,
          "barking-tendencies": 0,
          "cat-social": 0,
          "child-social": 0,
          "dog-social": 0,
          "exercise-needs": 0,
          "grooming": 0,
          "hypoallergenic": 0,
          "human-social": 0,
          "shedding": 0,
          "stranger-social": 0,
          "trainable": 0
        }
      }
    },
    {
      "n02109961-Eskimo_dog": {
        "metadata": {
          "size": 0,
          "apartment-friendly": 0,
          "barking-tendencies": 0,
          "cat-social": 0,
          "child-social": 0,
          "dog-social": 0,
          "exercise-needs": 0,
          "grooming": 0,
          "hypoallergenic": 0,
          "human-social": 0,
          "shedding": 0,
          "stranger-social": 0,
          "trainable": 0
        }
      }
    },
    {
      "n02110063-malamute": {
        "metadata": {
          "size": 0,
          "apartment-friendly": 0,
          "barking-tendencies": 0,
          "cat-social": 0,
          "child-social": 0,
          "dog-social": 0,
          "exercise-needs": 0,
          "grooming": 0,
          "hypoallergenic": 0,
          "human-social": 0,
          "shedding": 0,
          "stranger-social": 0,
          "trainable": 0
        }
      }
    },
    {
      "n02110185-Siberian_husky": {
        "metadata": {
          "size": 0,
          "apartment-friendly": 0,
          "barking-tendencies": 0,
          "cat-social": 0,
          "child-social": 0,
          "dog-social": 0,
          "exercise-needs": 0,
          "grooming": 0,
          "hypoallergenic": 0,
          "human-social": 0,
          "shedding": 0,
          "stranger-social": 0,
          "trainable": 0
        }
      }
    },
    {
      "n02110627-affenpinscher": {
        "metadata": {
          "size": 0,
          "apartment-friendly": 0,
          "barking-tendencies": 0,
          "cat-social": 0,
          "child-social": 0,
          "dog-social": 0,
          "exercise-needs": 0,
          "grooming": 0,
          "hypoallergenic": 0,
          "human-social": 0,
          "shedding": 0,
          "stranger-social": 0,
          "trainable": 0
        }
      }
    },
    {
      "n02110806-basenji": {
        "metadata": {
          "size": 0,
          "apartment-friendly": 0,
          "barking-tendencies": 0,
          "cat-social": 0,
          "child-social": 0,
          "dog-social": 0,
          "exercise-needs": 0,
          "grooming": 0,
          "hypoallergenic": 0,
          "human-social": 0,
          "shedding": 0,
          "stranger-social": 0,
          "trainable": 0
        }
      }
    },
    {
      "n02110958-pug": {
        "metadata": {
          "size": 0,
          "apartment-friendly": 0,
          "barking-tendencies": 0,
          "cat-social": 0,
          "child-social": 0,
          "dog-social": 0,
          "exercise-needs": 0,
          "grooming": 0,
          "hypoallergenic": 0,
          "human-social": 0,
          "shedding": 0,
          "stranger-social": 0,
          "trainable": 0
        }
      }
    },
    {
      "n02111129-Leonberg": {
        "metadata": {
          "size": 0,
          "apartment-friendly": 0,
          "barking-tendencies": 0,
          "cat-social": 0,
          "child-social": 0,
          "dog-social": 0,
          "exercise-needs": 0,
          "grooming": 0,
          "hypoallergenic": 0,
          "human-social": 0,
          "shedding": 0,
          "stranger-social": 0,
          "trainable": 0
        }
      }
    },
    {
      "n02111277-Newfoundland": {
        "metadata": {
          "size": 0,
          "apartment-friendly": 0,
          "barking-tendencies": 0,
          "cat-social": 0,
          "child-social": 0,
          "dog-social": 0,
          "exercise-needs": 0,
          "grooming": 0,
          "hypoallergenic": 0,
          "human-social": 0,
          "shedding": 0,
          "stranger-social": 0,
          "trainable": 0
        }
      }
    },
    {
      "n02111500-Great_Pyrenees": {
        "metadata": {
          "size": 0,
          "apartment-friendly": 0,
          "barking-tendencies": 0,
          "cat-social": 0,
          "child-social": 0,
          "dog-social": 0,
          "exercise-needs": 0,
          "grooming": 0,
          "hypoallergenic": 0,
          "human-social": 0,
          "shedding": 0,
          "stranger-social": 0,
          "trainable": 0
        }
      }
    },
    {
      "n02111889-Samoyed": {
        "metadata": {
          "size": 0,
          "apartment-friendly": 0,
          "barking-tendencies": 0,
          "cat-social": 0,
          "child-social": 0,
          "dog-social": 0,
          "exercise-needs": 0,
          "grooming": 0,
          "hypoallergenic": 0,
          "human-social": 0,
          "shedding": 0,
          "stranger-social": 0,
          "trainable": 0
        }
      }
    },
    {
      "n02112018-Pomeranian": {
        "metadata": {
          "size": 0,
          "apartment-friendly": 0,
          "barking-tendencies": 0,
          "cat-social": 0,
          "child-social": 0,
          "dog-social": 0,
          "exercise-needs": 0,
          "grooming": 0,
          "hypoallergenic": 0,
          "human-social": 0,
          "shedding": 0,
          "stranger-social": 0,
          "trainable": 0
        }
      }
    },
    {
      "n02112137-chow": {
        "metadata": {
          "size": 0,
          "apartment-friendly": 0,
          "barking-tendencies": 0,
          "cat-social": 0,
          "child-social": 0,
          "dog-social": 0,
          "exercise-needs": 0,
          "grooming": 0,
          "hypoallergenic": 0,
          "human-social": 0,
          "shedding": 0,
          "stranger-social": 0,
          "trainable": 0
        }
      }
    },
    {
      "n02112350-keeshond": {
        "metadata": {
          "size": 0,
          "apartment-friendly": 0,
          "barking-tendencies": 0,
          "cat-social": 0,
          "child-social": 0,
          "dog-social": 0,
          "exercise-needs": 0,
          "grooming": 0,
          "hypoallergenic": 0,
          "human-social": 0,
          "shedding": 0,
          "stranger-social": 0,
          "trainable": 0
        }
      }
    },
    {
      "n02112706-Brabancon_griffon": {
        "metadata": {
          "size": 0,
          "apartment-friendly": 0,
          "barking-tendencies": 0,
          "cat-social": 0,
          "child-social": 0,
          "dog-social": 0,
          "exercise-needs": 0,
          "grooming": 0,
          "hypoallergenic": 0,
          "human-social": 0,
          "shedding": 0,
          "stranger-social": 0,
          "trainable": 0
        }
      }
    },
    {
      "n02113023-Pembroke": {
        "metadata": {
          "size": 0,
          "apartment-friendly": 0,
          "barking-tendencies": 0,
          "cat-social": 0,
          "child-social": 0,
          "dog-social": 0,
          "exercise-needs": 0,
          "grooming": 0,
          "hypoallergenic": 0,
          "human-social": 0,
          "shedding": 0,
          "stranger-social": 0,
          "trainable": 0
        }
      }
    },
    {
      "n02113186-Cardigan": {
        "metadata": {
          "size": 0,
          "apartment-friendly": 0,
          "barking-tendencies": 0,
          "cat-social": 0,
          "child-social": 0,
          "dog-social": 0,
          "exercise-needs": 0,
          "grooming": 0,
          "hypoallergenic": 0,
          "human-social": 0,
          "shedding": 0,
          "stranger-social": 0,
          "trainable": 0
        }
      }
    },
    {
      "n02113624-toy_poodle": {
        "metadata": {
          "size": 0,
          "apartment-friendly": 0,
          "barking-tendencies": 0,
          "cat-social": 0,
          "child-social": 0,
          "dog-social": 0,
          "exercise-needs": 0,
          "grooming": 0,
          "hypoallergenic": 0,
          "human-social": 0,
          "shedding": 0,
          "stranger-social": 0,
          "trainable": 0
        }
      }
    },
    {
      "n02113712-miniature_poodle": {
        "metadata": {
          "size": 0,
          "apartment-friendly": 0,
          "barking-tendencies": 0,
          "cat-social": 0,
          "child-social": 0,
          "dog-social": 0,
          "exercise-needs": 0,
          "grooming": 0,
          "hypoallergenic": 0,
          "human-social": 0,
          "shedding": 0,
          "stranger-social": 0,
          "trainable": 0
        }
      }
    },
    {
      "n02113799-standard_poodle": {
        "metadata": {
          "size": 0,
          "apartment-friendly": 0,
          "barking-tendencies": 0,
          "cat-social": 0,
          "child-social": 0,
          "dog-social": 0,
          "exercise-needs": 0,
          "grooming": 0,
          "hypoallergenic": 0,
          "human-social": 0,
          "shedding": 0,
          "stranger-social": 0,
          "trainable": 0
        }
      }
    },
    {
      "n02113978-Mexican_hairless": {
        "metadata": {
          "size": 0,
          "apartment-friendly": 0,
          "barking-tendencies": 0,
          "cat-social": 0,
          "child-social": 0,
          "dog-social": 0,
          "exercise-needs": 0,
          "grooming": 0,
          "hypoallergenic": 0,
          "human-social": 0,
          "shedding": 0,
          "stranger-social": 0,
          "trainable": 0
        }
      }
    },
    {
      "n02115641-dingo": {
        "metadata": {
          "size": 0,
          "apartment-friendly": 0,
          "barking-tendencies": 0,
          "cat-social": 0,
          "child-social": 0,
          "dog-social": 0,
          "exercise-needs": 0,
          "grooming": 0,
          "hypoallergenic": 0,
          "human-social": 0,
          "shedding": 0,
          "stranger-social": 0,
          "trainable": 0
        }
      }
    },
    {
      "n02115913-dhole": {
        "metadata": {
          "size": 0,
          "apartment-friendly": 0,
          "barking-tendencies": 0,
          "cat-social": 0,
          "child-social": 0,
          "dog-social": 0,
          "exercise-needs": 0,
          "grooming": 0,
          "hypoallergenic": 0,
          "human-social": 0,
          "shedding": 0,
          "stranger-social": 0,
          "trainable": 0
        }
      }
    }
  ]
}
